ezissue/__init__.py
ezissue/ezissue.py
ezissue/utils.py
ezissue/converter/__init__.py
ezissue/converter/manipulation.py
ezissue/secops/__init__.py
ezissue/secops/secops_basic.py
tests/__init__.py
tests/test_issue_conv.py
tests/test_secops.py
ezissue_br-1.0.0.dist-info/LICENSE
ezissue_br-1.0.0.dist-info/METADATA
ezissue_br-1.0.0.dist-info/WHEEL
ezissue_br-1.0.0.dist-info/entry_points.txt
ezissue_br-1.0.0.dist-info/top_level.txt
ezissue_br-1.0.0.dist-info/RECORD
