Metadata-Version: 2.1
Name: ezissue-br
Version: 1.0.0
Summary: The ultimate aid in the issue creation process.
Home-page: https://github.com/andre-filho/ezissue
Author: Andre de Sousa Costa Filho
Author-email: andre.filho001@outlook.com
License: GNU
Keywords: ezissue-br,issue,markdown,api,github,gitlab,markdown to issue converter,pt-br
Platform: UNKNOWN
Classifier: Development Status :: 5 - Production/Stable
Classifier: Intended Audience :: Developers
Classifier: Natural Language :: Portuguese
Classifier: License :: OSI Approved :: GNU General Public License v3 or later (GPLv3+)
Classifier: Operating System :: OS Independent
Classifier: Programming Language :: Python
Classifier: Programming Language :: Python :: 3.6
Classifier: Programming Language :: Python :: Implementation :: CPython
Classifier: Programming Language :: Python :: Implementation :: PyPy
Classifier: Topic :: Software Development :: Libraries :: Python Modules
Requires-Dist: asn1crypto (~=0.24.0)
Requires-Dist: certifi (~=2019.3.9)
Requires-Dist: cffi (~=1.12.3)
Requires-Dist: chardet (~=3.0.4)
Requires-Dist: Click (~=7.0)
Requires-Dist: cryptography (~=2.6.1)
Requires-Dist: python-dotenv (~=0.10.2)
Requires-Dist: idna (~=2.8)
Requires-Dist: pycparser (~=2.19)
Requires-Dist: requests (~=2.21.0)
Requires-Dist: six (~=1.12.0)
Requires-Dist: urllib3 (~=1.24)
Requires-Dist: colored (~=1.3.93)
